[
    {
     "id": 1,
     "name": "Primer Vino",
     "price": "900",
     "discount": "3",
     "category": "in-sale",
     "description": "El mejor vino de DON ANTONIO, que le gusta tomar escabio en dock sud",
     "image": "red-wine.jpg"
    },
    {
        "id": 2,
        "name": "Segundo Vino",
        "price": "800",
        "discount": "3",
        "category": "in-sale",
        "description": "El mejor vino de DON ANTONIO, que le gusta tomar escabio en barracas",
        "image": "red-wine.jpg"
       },
       {
        "id": 3,
        "name": "Tercer Vino",
        "price": "700",
        "discount": "3",
        "category": "in-sale",
        "description": "El mejor vino de DON ANTONIO, que le gusta tomar escabio en la villa",
        "image": "red-wine.jpg"
       },
       {
        "id": 4,
        "name": "Cuarto Vino",
        "price": "600",
        "discount": "3",
        "category": "in-sale",
        "description": "El mejor vino de DON ANTONIO, que le gusta tomar escabio en bolivia",
        "image": "red-wine.jpg"
       }
    ]